README.rst
setup.cfg
setup.py
pyg3D/AnimationManager.py
pyg3D/Camera.py
pyg3D/Light.py
pyg3D/Materials.py
pyg3D/Object2D.py
pyg3D/Object3D.py
pyg3D/ObjectManager.py
pyg3D/Primitive.py
pyg3D/VectorFunctions.py
pyg3D/__init__.py
pyg3D/opengl.py
pyg3D.egg-info/PKG-INFO
pyg3D.egg-info/SOURCES.txt
pyg3D.egg-info/dependency_links.txt
pyg3D.egg-info/requires.txt
pyg3D.egg-info/top_level.txt
pywavefront/__init__.py
pywavefront/material.py
pywavefront/mesh.py
pywavefront/parser.py
pywavefront/texture.py