Metadata-Version: 2.1
Name: pyg3D
Version: 1.0.2
Summary: A simple 3D rendering library for python
Home-page: https://gitlab.com/ll13s5h/pyg3D
Author: Sam H
Author-email: ll13s5h@leeds.ac.uk
License: UNKNOWN
Keywords: simple 3D games graphics
Platform: UNKNOWN
Classifier: Development Status :: 3 - Alpha
Classifier: Intended Audience :: Developers
Classifier: Topic :: Software Development
Classifier: License :: OSI Approved :: BSD License
Classifier: Programming Language :: Python :: 3
Requires-Python: >=3
